snowplow/__init__.py
snowplow/cli.py
snowplow/commands/__init__.py
snowplow/commands/compare_csv/__init__.py
snowplow/commands/compare_csv/cli.py
snowplow/commands/compare_csv/compare_csv.py
snowplow/commands/compare_s3/__init__.py
snowplow/commands/compare_s3/cli.py
snowplow/commands/compare_s3/compare_s3.py
snowplow/commands/list_local/__init__.py
snowplow/commands/list_local/cli.py
snowplow/commands/list_local/list_local.py
snowplow/commands/list_s3/__init__.py
snowplow/commands/list_s3/cli.py
snowplow/commands/list_s3/list_s3.py
snowplow/commands/new_instance/__init__.py
snowplow/commands/new_instance/cli.py
snowplow/commands/new_instance/new_instance.py
snowplow/core/__init__.py
snowplow/core/env.py
snowplow/core/utils.py
snowplow-0.0b27.dist-info/LICENSE
snowplow-0.0b27.dist-info/METADATA
snowplow-0.0b27.dist-info/NOTICE
snowplow-0.0b27.dist-info/WHEEL
snowplow-0.0b27.dist-info/entry_points.txt
snowplow-0.0b27.dist-info/top_level.txt
snowplow-0.0b27.dist-info/RECORD
