Metadata-Version: 2.1
Name: snowplow
Version: 0.0b27
Summary: S3 to Synapse Orchestration
Home-page: https://github.com/ki-tools/snowplow
Author: Patrick Stout
Author-email: pstout@prevagroup.com
License: Apache2
Platform: UNKNOWN
Classifier: Programming Language :: Python
Classifier: Programming Language :: Python :: 3.7
Classifier: License :: OSI Approved :: Apache Software License
Classifier: Operating System :: OS Independent
Requires-Dist: boto3
